flask_annex/__init__.py
flask_annex/base.py
flask_annex/file.py
flask_annex/s3.py
flask_annex/utils.py
Flask_Annex-2.0.0.dist-info/LICENSE
Flask_Annex-2.0.0.dist-info/METADATA
Flask_Annex-2.0.0.dist-info/WHEEL
Flask_Annex-2.0.0.dist-info/top_level.txt
Flask_Annex-2.0.0.dist-info/RECORD
