Metadata-Version: 2.1
Name: Flask-Annex
Version: 2.0.0
Summary: Efficient integration of external storage services for Flask
Home-page: https://github.com/4Catalyzer/flask-annex
Author: Jimmy Jia
Author-email: tesrin@gmail.com
License: MIT
Keywords: storage s3 flask
Classifier: Framework :: Flask
Classifier: Environment :: Web Environment
Classifier: Intended Audience :: Developers
Classifier: License :: OSI Approved :: MIT License
Classifier: Operating System :: OS Independent
Classifier: Programming Language :: Python
Classifier: Programming Language :: Python :: 3
Classifier: Programming Language :: Python :: 3.10
Classifier: Programming Language :: Python :: 3.11
Classifier: Programming Language :: Python :: 3.12
Classifier: Programming Language :: Python :: 3 :: Only
Classifier: Topic :: Internet :: WWW/HTTP :: Dynamic Content
Classifier: Topic :: Software Development :: Libraries :: Python Modules
Requires-Python: >=3.10
License-File: LICENSE
Requires-Dist: Flask >=2.0
Requires-Dist: packaging >=17.0
Provides-Extra: s3
Requires-Dist: boto3 >=1.4.0 ; extra == 's3'
Provides-Extra: tests
Requires-Dist: pytest ; extra == 'tests'
Requires-Dist: pytest-cov ; extra == 'tests'
Provides-Extra: tests-s3
Requires-Dist: moto ; extra == 'tests-s3'
Requires-Dist: requests ; extra == 'tests-s3'
